{
  "id": 1,
  "title": "Google 面試準備",
  "src": "",
  "last_update": "2026-05-20T03:34:42.164Z",
  "summary": "這份 Google 面試準備題單不只列題，也把每一章的「觀念說明」整理成可直接複習的筆記。展開章節後，你會看到：何時使用這類技巧、面試中要先問自己的判斷問題、常見複雜度，以及可改寫到題目中的 C++ 模板。\n\n建議做法：先讀觀念說明，再限時做題；做完後用模板反推自己的程式碼，確認狀態、邊界、不變式與複雜度都能口頭說清楚。",
  "children": [
    {
      "id": 2,
      "title": "1. 圖搜尋與最短路",
      "summary": "這章處理「狀態可以走到哪些下一步」的題型。面試時先不要急著套 BFS 或 Dijkstra，先回答三件事：狀態是什麼、邊的代價是否相同、visited 是否需要記錄額外維度。\n\n**判斷流程**：\n- 所有邊代價相同：用 BFS。\n- 邊代價只有 0/1：用 0-1 BFS。\n- 邊代價為非負整數：用 Dijkstra。\n- 問連通性或逐步合併：考慮並查集。\n- 網格題的狀態不一定只有 \\(r,c\\)，可能還要包含剩餘消除次數、鑰匙集合、方向或目前時間。\n\n**C++：網格 BFS（狀態含額外資源）**\n\n```cpp\nint shortestPath(vector<vector<int>>& grid, int k) {\n    int m = grid.size(), n = grid[0].size();\n    vector<vector<int>> best(m, vector<int>(n, -1));\n    queue<array<int, 4>> q; // r, c, remaining_k, dist\n    q.push({0, 0, k, 0});\n    best[0][0] = k;\n\n    int dirs[5] = {1, 0, -1, 0, 1};\n    while (!q.empty()) {\n        auto [r, c, left, dist] = q.front();\n        q.pop();\n        if (r == m - 1 && c == n - 1) return dist;\n\n        for (int d = 0; d < 4; ++d) {\n            int nr = r + dirs[d], nc = c + dirs[d + 1];\n            if (nr < 0 || nr >= m || nc < 0 || nc >= n) continue;\n            int nextLeft = left - grid[nr][nc];\n            if (nextLeft < 0) continue;\n            if (best[nr][nc] >= nextLeft) continue;\n            best[nr][nc] = nextLeft;\n            q.push({nr, nc, nextLeft, dist + 1});\n        }\n    }\n    return -1;\n}\n```\n\n**C++：Dijkstra（非負權最短路）**\n\n```cpp\nvector<long long> dijkstra(int n, vector<vector<pair<int, int>>>& g, int src) {\n    const long long INF = 4e18;\n    vector<long long> dist(n, INF);\n    priority_queue<pair<long long, int>, vector<pair<long long, int>>, greater<>> pq;\n    dist[src] = 0;\n    pq.push({0, src});\n\n    while (!pq.empty()) {\n        auto [du, u] = pq.top();\n        pq.pop();\n        if (du != dist[u]) continue;\n\n        for (auto [v, w] : g[u]) {\n            if (dist[v] > du + w) {\n                dist[v] = du + w;\n                pq.push({dist[v], v});\n            }\n        }\n    }\n    return dist;\n}\n```\n\n複雜度：BFS 通常是 \\(O(狀態數 + 轉移數)\\)，Dijkstra 是 \\(O((V+E)\\log V)\\)。",
      "children": []
    },
    {
      "id": 3,
      "title": "2. 樹與圖建模",
      "summary": "這章訓練把題目文字轉成圖、樹或 DAG。Google 題常把「人、會議、課程、城市、父子關係」包成關係資料；正確建模後，解法通常會變成 DFS、拓撲排序、樹形 DP、Tarjan 或換根。\n\n**建模檢查表**：\n- 關係是否有方向？如果有方向，是否可能有環？\n- 如果是樹，根是固定的還是任選的？答案是否會因換根改變？\n- 子樹答案能否由孩子合併？是否需要把父側資訊再傳回孩子？\n- 圖中是否要找橋、割點或強連通分量？\n\n**C++：拓撲排序 + DAG 最長時間**\n\n```cpp\nint minimumTime(int n, vector<vector<int>>& relations, vector<int>& time) {\n    vector<vector<int>> g(n);\n    vector<int> indeg(n), finish(n);\n    for (auto& e : relations) {\n        int u = e[0] - 1, v = e[1] - 1;\n        g[u].push_back(v);\n        indeg[v]++;\n    }\n\n    queue<int> q;\n    for (int i = 0; i < n; ++i) {\n        finish[i] = time[i];\n        if (indeg[i] == 0) q.push(i);\n    }\n\n    while (!q.empty()) {\n        int u = q.front();\n        q.pop();\n        for (int v : g[u]) {\n            finish[v] = max(finish[v], finish[u] + time[v]);\n            if (--indeg[v] == 0) q.push(v);\n        }\n    }\n    return *max_element(finish.begin(), finish.end());\n}\n```\n\n**C++：樹形 DFS，回傳子樹資訊**\n\n```cpp\nlong long answer = 0;\n\nlong long dfs(int u, int parent, vector<vector<int>>& tree, vector<int>& value) {\n    long long subtotal = value[u];\n    for (int v : tree[u]) {\n        if (v == parent) continue;\n        subtotal += dfs(v, u, tree, value);\n    }\n\n    // 在這裡根據 subtotal 更新答案，例如切出可行連通塊。\n    if (subtotal % 3 == 0) {\n        answer++;\n        return 0;\n    }\n    return subtotal;\n}\n```\n\n**C++：Tarjan 找橋**\n\n```cpp\nvector<vector<int>> bridges;\nvector<int> dfn, low;\nint timer = 0;\n\nvoid tarjan(int u, int parentEdge, vector<vector<pair<int, int>>>& g) {\n    dfn[u] = low[u] = ++timer;\n    for (auto [v, eid] : g[u]) {\n        if (eid == parentEdge) continue;\n        if (!dfn[v]) {\n            tarjan(v, eid, g);\n            low[u] = min(low[u], low[v]);\n            if (low[v] > dfn[u]) bridges.push_back({u, v});\n        } else {\n            low[u] = min(low[u], dfn[v]);\n        }\n    }\n}\n```",
      "children": []
    },
    {
      "id": 4,
      "title": "3. 動態規劃與搜尋優化",
      "summary": "這章的核心是把暴力搜尋改成「只記必要資訊」。先定義狀態，再判斷狀態之間如何轉移；如果狀態數太大，再找排序、前綴和、二分、單調性或狀態壓縮。\n\n**DP 設計步驟**：\n1. 定義狀態：目前處理到哪裡？還剩什麼限制？答案需要最大、最小還是計數？\n2. 找最後一步：最後選了什麼、接在哪個狀態後面？\n3. 寫初始值與非法值：最小化常用 INF，最大化常用負無限。\n4. 壓縮空間前，先確認轉移只依賴上一層或固定方向。\n\n**C++：帶權區間排程 DP**\n\n```cpp\nint jobScheduling(vector<int>& start, vector<int>& end, vector<int>& profit) {\n    int n = start.size();\n    vector<array<int, 3>> jobs;\n    for (int i = 0; i < n; ++i) jobs.push_back({end[i], start[i], profit[i]});\n    sort(jobs.begin(), jobs.end());\n\n    vector<int> ends(n), dp(n + 1);\n    for (int i = 0; i < n; ++i) ends[i] = jobs[i][0];\n\n    for (int i = 1; i <= n; ++i) {\n        auto [e, s, p] = jobs[i - 1];\n        int j = upper_bound(ends.begin(), ends.end(), s) - ends.begin();\n        dp[i] = max(dp[i - 1], dp[j] + p);\n    }\n    return dp[n];\n}\n```\n\n**C++：狀壓 DP（集合覆蓋）**\n\n```cpp\nvector<int> smallestSufficientTeam(vector<string>& req, vector<vector<string>>& people) {\n    int m = req.size();\n    unordered_map<string, int> id;\n    for (int i = 0; i < m; ++i) id[req[i]] = i;\n\n    int full = 1 << m;\n    vector<vector<int>> dp(full);\n    vector<char> seen(full);\n    seen[0] = true;\n\n    for (int i = 0; i < (int)people.size(); ++i) {\n        int mask = 0;\n        for (auto& skill : people[i]) mask |= 1 << id[skill];\n        auto old = dp;\n        auto oldSeen = seen;\n        for (int s = 0; s < full; ++s) {\n            if (!oldSeen[s]) continue;\n            int ns = s | mask;\n            if (!seen[ns] || old[s].size() + 1 < dp[ns].size()) {\n                dp[ns] = old[s];\n                dp[ns].push_back(i);\n                seen[ns] = true;\n            }\n        }\n    }\n    return dp[full - 1];\n}\n```\n\n複雜度通常由「狀態數 × 每個狀態的轉移數」決定。面試中要能明確說出狀態是否覆蓋所有可能，以及為什麼不重不漏。",
      "children": []
    },
    {
      "id": 5,
      "title": "4. 字串、Trie 與雜湊",
      "summary": "字串題的第一步是判斷「比較單位」。如果比較前綴/後綴，可用 KMP 或 Z 函式；如果比較大量子串，可用 rolling hash；如果要反覆走字典中的字首，可用 Trie；如果是字串轉換，通常要建圖後跑最短路或 DP。\n\n**常見選型**：\n- 找 pattern 在 text 中出現：KMP / Z。\n- 快速比較兩段子串是否相等：rolling hash。\n- 多個字典詞匹配 target 的前綴：Trie + DP/BFS。\n- 字元或字串替換有代價：建圖後最短路，再做 DP。\n\n**C++：KMP 前綴函式**\n\n```cpp\nvector<int> prefixFunction(const string& s) {\n    int n = s.size();\n    vector<int> pi(n);\n    for (int i = 1; i < n; ++i) {\n        int j = pi[i - 1];\n        while (j > 0 && s[i] != s[j]) j = pi[j - 1];\n        if (s[i] == s[j]) j++;\n        pi[i] = j;\n    }\n    return pi;\n}\n\nvector<int> findMatches(const string& text, const string& pat) {\n    string s = pat + '#' + text;\n    vector<int> pi = prefixFunction(s), ans;\n    int m = pat.size();\n    for (int i = m + 1; i < (int)s.size(); ++i) {\n        if (pi[i] == m) ans.push_back(i - 2 * m);\n    }\n    return ans;\n}\n```\n\n**C++：Trie + DP 最少拼接數**\n\n```cpp\nstruct TrieNode {\n    int next[26];\n    bool end = false;\n    TrieNode() { memset(next, -1, sizeof(next)); }\n};\n\nint minWords(vector<string>& words, string target) {\n    vector<TrieNode> trie(1);\n    for (auto& w : words) {\n        int u = 0;\n        for (char ch : w) {\n            int c = ch - 'a';\n            if (trie[u].next[c] == -1) {\n                trie[u].next[c] = trie.size();\n                trie.emplace_back();\n            }\n            u = trie[u].next[c];\n        }\n        trie[u].end = true;\n    }\n\n    const int INF = 1e9;\n    int n = target.size();\n    vector<int> dp(n + 1, INF);\n    dp[0] = 0;\n    for (int i = 0; i < n; ++i) {\n        if (dp[i] == INF) continue;\n        int u = 0;\n        for (int j = i; j < n; ++j) {\n            int c = target[j] - 'a';\n            if (trie[u].next[c] == -1) break;\n            u = trie[u].next[c];\n            if (trie[u].end) dp[j + 1] = min(dp[j + 1], dp[i] + 1);\n        }\n    }\n    return dp[n] == INF ? -1 : dp[n];\n}\n```",
      "children": []
    },
    {
      "id": 6,
      "title": "5. 資料結構與離線處理",
      "summary": "資料結構題的關鍵不是認出容器名稱，而是維護不變式。每次操作後，資料結構必須仍能快速回答題目需要的最大值、最小值、歷史值、區間交集或第 k 個元素。\n\n**選型提示**：\n- 需要動態最大/最小：heap，若有刪除舊值，使用懶刪除。\n- 需要有序前驅/後繼：set / map。\n- 需要歷史版本查詢：每個位置存時間序列，再二分。\n- 查詢可離線排序：把資料和 query 依門檻排序，逐步加入候選集合。\n\n**C++：懶刪除最大堆**\n\n```cpp\npriority_queue<pair<long long, int>> pq; // value, id\nunordered_map<int, long long> current;\n\nvoid update(int id, long long value) {\n    current[id] = value;\n    pq.push({value, id});\n}\n\nlong long getMax() {\n    while (!pq.empty()) {\n        auto [value, id] = pq.top();\n        if (current.count(id) && current[id] == value) return value;\n        pq.pop();\n    }\n    return 0;\n}\n```\n\n**C++：Snapshot Array 核心做法**\n\n```cpp\nclass SnapshotArray {\n    int snapId = 0;\n    vector<vector<pair<int, int>>> history;\n\npublic:\n    SnapshotArray(int length) : history(length, {{0, 0}}) {}\n\n    void set(int index, int val) {\n        if (history[index].back().first == snapId) {\n            history[index].back().second = val;\n        } else {\n            history[index].push_back({snapId, val});\n        }\n    }\n\n    int snap() { return snapId++; }\n\n    int get(int index, int id) {\n        auto& h = history[index];\n        int pos = upper_bound(h.begin(), h.end(), pair<int, int>{id, INT_MAX}) - h.begin() - 1;\n        return h[pos].second;\n    }\n};\n```\n\n離線題常見複雜度是排序 \\(O((n+q)\\log(n+q))\\) 加上資料結構操作；設計前先確認 query 可否重排，答案是否只依賴門檻而不依賴原順序。",
      "children": []
    },
    {
      "id": 7,
      "title": "6. 二分、貪心與滑動視窗",
      "summary": "這章處理「答案不是直接算，而是要找邊界或維護一段窗口」的題型。二分答案需要單調性，貪心需要可證明的局部選擇，滑動視窗需要能在左右指標移動時維護合法性。\n\n**快速判斷**：\n- 問最大化最小值、最小化最大值、最多能撐多久：考慮二分答案。\n- 排序後做選擇，局部選擇能用交換論證證明：考慮貪心。\n- 子陣列/子字串條件隨右端點擴張、左端點收縮：考慮滑動視窗。\n\n**C++：二分答案模板**\n\n```cpp\nbool feasible(long long x, vector<int>& nums) {\n    // 回傳答案至少/至多為 x 時是否可行。\n    // 必須滿足單調性：若 x 可行，某一側全部可行。\n    return true;\n}\n\nlong long binaryAnswer(vector<int>& nums) {\n    long long lo = 0, hi = 1e18;\n    while (lo < hi) {\n        long long mid = lo + (hi - lo) / 2;\n        if (feasible(mid, nums)) {\n            hi = mid;\n        } else {\n            lo = mid + 1;\n        }\n    }\n    return lo;\n}\n```\n\n**C++：滑動視窗（至多 k 個壞元素）**\n\n```cpp\nint longestWindow(vector<int>& nums, int k) {\n    int left = 0, bad = 0, ans = 0;\n    for (int right = 0; right < (int)nums.size(); ++right) {\n        if (nums[right] == 0) bad++;\n        while (bad > k) {\n            if (nums[left] == 0) bad--;\n            left++;\n        }\n        ans = max(ans, right - left + 1);\n    }\n    return ans;\n}\n```\n\n**C++：交換論證型排序骨架**\n\n```cpp\nstruct Job {\n    long long cost;\n    long long weight;\n};\n\nsort(jobs.begin(), jobs.end(), [](const Job& a, const Job& b) {\n    // 比較 a 在前與 b 在前的總代價。\n    return a.cost * b.weight < b.cost * a.weight;\n});\n```\n\n面試中要主動說明單調性或交換論證；只說「看起來可以二分/貪心」通常不夠。",
      "children": []
    }
  ]
}
